[
  {
    "model": "app_market.book",
    "pk": 1,
    "fields": {
      "title": "Низший",
      "author": 2,
      "description": "Аннотация: Безымянный мир, где рождаешься уже взрослым и в долгах. Мир, где даже твои руки и ноги тебе не принадлежат, а являются собственностью бездушной системы. Безумно жестокий мир, где жизнь не стоит ни единого сола, где ты добровольно низший со стертой памятью, где за ошибки, долги и преступления тебя лишают конечности за конечностью, медленно превращая в беспомощного червя с человеческим лицом... Мир со стальными небом и землей, с узкими давящими стенами, складывающимися в бесконечный стальной лабиринт. Мир, где в торговых автоматах продают шизу и дубины, где за тобой охотятся кровожадные безголовые плуксы, а самая страшная участь - превратиться в откормленную свинью...",
      "price": "75.00",
      "cycle": 2,
      "authors_note": "Исправленная версия.",
      "create_date": "2024-06-01T14:19:04.279Z",
      "update_date": "2024-06-01T14:19:04.279Z",
      "slug": "2-nizshij",
      "tags": [
        1,
        2,
        3
      ],
      "genre": [
        5,
        7,
        6
      ]
    }
  },
  {
    "model": "app_market.book",
    "pk": 2,
    "fields": {
      "title": "Низший 2",
      "author": 2,
      "description": "Роман в жанре РеалРПГ - как я его понимаю. Жанр для меня новый. Роман ЖЕСТКИЙ! Местами ЖЕСТОКИЙ! И это черный жуткий мир! Кровь, расчлененка, всем плевать на всех и на все.  Гоблин Оди — он же номер одиннадцатый — далеко не обычный трусливый гоблин. Он с готовностью нарывается на неприятности и не боится убивать и быть жестоким. Продвигаясь шаг за шагом, он с каждым днем узнает все больше о Безымянном мире и тварях его населяющих. Он сплачивает вокруг себя верных соратников, отбирая их только по ему понятным критериям. Однорукая озлобленная гоблинша? Прекрасно! Слепой зомби? Идеальный напарник. Каждый шаг гоблина с цифрой 11 на груди отмечен кровью. И с каждым новым шагом крови только прибавляется. А злобный гоблин довольно скалится — лопнуть и сдохнуть! Больше крови, больше! Пусть весь этот долбанный уродливый мир потонет в крови!",
      "price": "90.00",
      "cycle": 2,
      "authors_note": "1. Низший начат 1 сентября. Закончен 22 сентября того же года. 2. Низший-2 начат 22 сентября. Закончен 12 октября того же года.",
      "create_date": "2024-06-01T14:21:14.881Z",
      "update_date": "2024-06-01T14:21:14.881Z",
      "slug": "2-nizshij-2",
      "tags": [
        1,
        3,
        4,
        5
      ],
      "genre": [
        5,
        7,
        6
      ]
    }
  },
  {
    "model": "app_market.book",
    "pk": 3,
    "fields": {
      "title": "Чернокнижник. Неистовый маг 1",
      "author": 3,
      "description": "Попаданец в магический мир. Человек, который ищет силы. Тот, кто считает, что даже самые темные и страшные знания в правильных руках могут сослужить добрую службу. Он - чернокнижник. И горе тем, кто встанет у него на пути.  Прав ли он или жестоко ошибается? Лишь читающий эти строки узнает ответ.",
      "price": "100.00",
      "cycle": 3,
      "authors_note": "Первая книга бесплатная, поэтому автор был бы рад поддержки книги лайком и подпиской на профиль автора.) ✅ Сайт-иллюстрация:",
      "create_date": "2024-06-01T14:23:37.067Z",
      "update_date": "2024-06-01T14:23:37.067Z",
      "slug": "3-chernoknizhnik-neistovyj-mag-1",
      "tags": [
        6,
        7,
        8,
        9
      ],
      "genre": [
        2,
        4
      ]
    }
  },
  {
    "model": "app_market.book",
    "pk": 4,
    "fields": {
      "title": "Чернокнижник. Неистовый маг 2",
      "author": 3,
      "description": "Империя стремительно катится в ад. Армии наемников, война аристократов, столкновение магов и Орденов паладинов. Словно этого мало, кровавые призывы демонов гремят по всей стране.  В центре этой кровавой свистопляски Александр Вульфс. Его цель проста: узнать тайные, запретные знания. И он готов убить любого кто встанет у него на пути.",
      "price": "120.00",
      "cycle": 3,
      "authors_note": "✅ Лайки и подписки и впрямь побуждают автора писать больше и чаще.)",
      "create_date": "2024-06-01T14:24:58.902Z",
      "update_date": "2024-06-01T14:54:17.347Z",
      "slug": "3-chernoknizhnik-neistovyj-mag-2",
      "tags": [
        6,
        7,
        8,
        9
      ],
      "genre": [
        1,
        3,
        4
      ]
    }
  },
  {
    "model": "app_market.book",
    "pk": 5,
    "fields": {
      "title": "Попаданец в Дракона - 1",
      "author": 3,
      "description": "Я обожаю звон золота, что скользит меж моих когтей. Крики врагов, что сгорают в моём пламени, тешат мне душу. Излучаемый ими липкий страх, радует моё сердце. Если у вас есть проблема, заплатите мне, и она вас больше никогда не побеспокоит. И всё, что вы видите, рано или поздно будет принадлежать лишь мне.",
      "price": "100.00",
      "cycle": 1,
      "authors_note": "✅ Больше подписок на профиль автора, лайков и поддержки от читателей, тем стремительней пишутся книги.) ✅ Решил не мудрить с названием после того, как много людей не поняли метафору в Целителе чудовищ)",
      "create_date": "2024-06-01T14:26:32.644Z",
      "update_date": "2024-06-01T14:26:32.644Z",
      "slug": "3-popadanec-v-drakona-1",
      "tags": [
        10,
        11,
        12
      ],
      "genre": [
        2,
        4
      ]
    }
  },
  {
    "model": "app_market.book",
    "pk": 6,
    "fields": {
      "title": "Попаданец в Дракона - 2",
      "author": 3,
      "description": "Я обожаю звон золота, что скользит меж моих когтей. Крики врагов, что сгорают в моём пламени, тешат мне душу. Излучаемый ими липкий страх, радует моё сердце. Если у вас есть проблема, заплатите мне, и она вас больше никогда не побеспокоит. И всё, что вы видите, рано или поздно будет принадлежать лишь мне.",
      "price": "150.00",
      "cycle": 1,
      "authors_note": "✅ Больше подписок на профиль автора, лайков и поддержки от читателей, тем стремительней пишутся книги.)",
      "create_date": "2024-06-01T14:28:21.596Z",
      "update_date": "2024-06-01T14:28:21.596Z",
      "slug": "3-popadanec-v-drakona-2",
      "tags": [
        10,
        11,
        12
      ],
      "genre": [
        1,
        4
      ]
    }
  }
]